mcp_predictor/__init__.py
mcp_predictor-1.0.0.dist-info/METADATA
mcp_predictor-1.0.0.dist-info/WHEEL
mcp_predictor-1.0.0.dist-info/entry_points.txt
mcp_predictor-1.0.0.dist-info/top_level.txt
mcp_predictor-1.0.0.dist-info/RECORD
