Metadata-Version: 2.4
Name: mcp-predictor
Version: 1.0.0
Summary: Simple Time Series Prediction Library
Home-page: https://github.com/your-username/mcp-predictor
Author: MCP Predictor Team
Author-email: your-email@example.com
Classifier: Programming Language :: Python :: 3
Classifier: License :: OSI Approved :: MIT License
Classifier: Operating System :: OS Independent
Requires-Python: >=3.8
Requires-Dist: pandas>=2.0.0
Requires-Dist: numpy>=1.20.0
Requires-Dist: prophet>=1.1.0
Requires-Dist: lightgbm>=4.0.0
Requires-Dist: scikit-learn>=1.0.0
Requires-Dist: PyYAML>=6.0
Requires-Dist: ibm-db>=3.2.0
Requires-Dist: optuna>=4.0.0
Dynamic: author
Dynamic: author-email
Dynamic: classifier
Dynamic: description
Dynamic: description-content-type
Dynamic: home-page
Dynamic: requires-dist
Dynamic: requires-python
Dynamic: summary
